{
  "light": "#ffffff",
  "dark": "#02001d",
  "neutral": "#efefec",
  "neutralAlt": "#e0e0da",
  "primary": "#f65458",
  "fontBody": "sans",
  "fontHeadlines": "sans",
  "h1": {
    "size": "6xl",
    "weight": "normal",
    "decoration": "none",
    "case": "none",
    "letterSpacing": "normal",
    "__metadata": {
      "id": "3N4eAFB5idS1SBw5SkbKT7",
      "source": "sourcebit-source-contentful",
      "modelName": "ThemeStyleHeading",
      "projectId": "b7sdnz3e5n7a",
      "projectEnvironment": "master",
      "tags": [],
      "createdAt": "2023-01-03T09:25:42.588Z",
      "updatedAt": "2023-01-03T09:26:20.617Z"
    }
  },
  "h2": {
    "size": "5xl",
    "weight": "normal",
    "decoration": "none",
    "case": "none",
    "letterSpacing": "normal",
    "__metadata": {
      "id": "3JoBKVeAYbqY0QrSBgxcL4",
      "source": "sourcebit-source-contentful",
      "modelName": "ThemeStyleHeading",
      "projectId": "b7sdnz3e5n7a",
      "projectEnvironment": "master",
      "tags": [],
      "createdAt": "2023-01-03T09:25:44.655Z",
      "updatedAt": "2023-01-03T09:26:25.756Z"
    }
  },
  "h3": {
    "size": "3xl",
    "weight": "normal",
    "decoration": "none",
    "case": "none",
    "letterSpacing": "normal",
    "__metadata": {
      "id": "7F0C6ZNAsggQSsVDGAlZUC",
      "source": "sourcebit-source-contentful",
      "modelName": "ThemeStyleHeading",
      "projectId": "b7sdnz3e5n7a",
      "projectEnvironment": "master",
      "tags": [],
      "createdAt": "2023-01-03T09:25:41.591Z",
      "updatedAt": "2023-01-03T09:26:15.368Z"
    }
  },
  "h4": {
    "size": "2xl",
    "weight": "normal",
    "decoration": "none",
    "case": "none",
    "letterSpacing": "normal",
    "__metadata": {
      "id": "4MpuNuwMqPiR9Ar6qnyfr4",
      "source": "sourcebit-source-contentful",
      "modelName": "ThemeStyleHeading",
      "projectId": "b7sdnz3e5n7a",
      "projectEnvironment": "master",
      "tags": [],
      "createdAt": "2023-01-03T09:25:42.563Z",
      "updatedAt": "2023-01-03T09:26:19.004Z"
    }
  },
  "h5": {
    "size": "xl",
    "weight": "normal",
    "decoration": "none",
    "case": "none",
    "letterSpacing": "normal",
    "__metadata": {
      "id": "25k4XmQ6eyk1xme8qMyhm",
      "source": "sourcebit-source-contentful",
      "modelName": "ThemeStyleHeading",
      "projectId": "b7sdnz3e5n7a",
      "projectEnvironment": "master",
      "tags": [],
      "createdAt": "2023-01-03T09:25:40.606Z",
      "updatedAt": "2023-01-03T09:26:12.296Z"
    }
  },
  "h6": {
    "size": "lg",
    "weight": "normal",
    "decoration": "none",
    "case": "none",
    "letterSpacing": "normal",
    "__metadata": {
      "id": "7FyecFLPhkps6WtXTHz1Fu",
      "source": "sourcebit-source-contentful",
      "modelName": "ThemeStyleHeading",
      "projectId": "b7sdnz3e5n7a",
      "projectEnvironment": "master",
      "tags": [],
      "createdAt": "2023-01-03T09:25:40.601Z",
      "updatedAt": "2023-01-03T09:26:10.675Z"
    }
  },
  "buttonPrimary": {
    "weight": "normal",
    "case": "none",
    "letterSpacing": "normal",
    "borderRadius": "DEFAULT",
    "shadow": "none",
    "horizontalPadding": 30,
    "verticalPadding": 12,
    "__metadata": {
      "id": "8G2cmPodhnTDG1rYpL5AD",
      "source": "sourcebit-source-contentful",
      "modelName": "ThemeStyleButton",
      "projectId": "b7sdnz3e5n7a",
      "projectEnvironment": "master",
      "tags": [],
      "createdAt": "2023-01-03T09:25:40.587Z",
      "updatedAt": "2023-01-03T09:26:10.051Z"
    }
  },
  "buttonSecondary": {
    "weight": "normal",
    "case": "none",
    "letterSpacing": "normal",
    "borderRadius": "DEFAULT",
    "shadow": "none",
    "horizontalPadding": 30,
    "verticalPadding": 12,
    "__metadata": {
      "id": "7vDsI4ajCGHBTnkANKJebC",
      "source": "sourcebit-source-contentful",
      "modelName": "ThemeStyleButton",
      "projectId": "b7sdnz3e5n7a",
      "projectEnvironment": "master",
      "tags": [],
      "createdAt": "2023-01-03T09:25:44.525Z",
      "updatedAt": "2023-01-03T09:26:26.790Z"
    }
  },
  "linkPrimary": {
    "weight": "normal",
    "case": "none",
    "letterSpacing": "normal",
    "__metadata": {
      "id": "4RWGns9oyyafduJQSutNjB",
      "source": "sourcebit-source-contentful",
      "modelName": "ThemeStyleLink",
      "projectId": "b7sdnz3e5n7a",
      "projectEnvironment": "master",
      "tags": [],
      "createdAt": "2023-01-03T09:25:48.540Z",
      "updatedAt": "2023-01-03T09:26:42.655Z"
    }
  },
  "linkSecondary": {
    "weight": "normal",
    "case": "none",
    "letterSpacing": "normal",
    "__metadata": {
      "id": "4GHcJInr6s27ofQ9O8XSB6",
      "source": "sourcebit-source-contentful",
      "modelName": "ThemeStyleLink",
      "projectId": "b7sdnz3e5n7a",
      "projectEnvironment": "master",
      "tags": [],
      "createdAt": "2023-01-03T09:25:49.546Z",
      "updatedAt": "2023-01-03T09:26:45.360Z"
    }
  },
  "__metadata": {
    "id": "1MZJRBeITBM18j4MGKdE92",
    "source": "sourcebit-source-contentful",
    "modelName": "ThemeStyle",
    "projectId": "b7sdnz3e5n7a",
    "projectEnvironment": "master",
    "tags": [],
    "createdAt": "2023-01-03T09:25:55.582Z",
    "updatedAt": "2023-01-08T09:23:27.592Z"
  }
}